{
  "version": 1,
  "module1": {
    "mapTo": {
      "平台": "__fixed__",
      "平台订单号": "GSP订单号",
      "发货人姓名": "__fixed__",
      "发货人电话": "__fixed__",
      "发货人地址": "__fixed__",
      "发货人省份": "__fixed__",
      "发货人城市": "__fixed__",
      "发货邮编": "__fixed__",
      "收货人姓名": "用户全称",
      "收货人电话": "手机号",
      "收货人地址": "用户地址1",
      "收货人省份": "省份",
      "收货人城市": "城市",
      "收件人邮编": "邮编",
      "达到天数": "__fixed__",
      "商品ID": "商品ID",
      "重量(kg)": "__fixed__",
      "数量": "__fixed__",
      "货值(元)": "__fixed__",
      "备注": "__fixed__"
    },
    "fixed": {
      "平台": "shein",
      "平台订单号": "",
      "发货人姓名": "JOHN LEAVY",
      "发货人电话": "（+1）123456789",
      "发货人地址": "133-11 FRANCLS  LEWIS BLVD",
      "发货人省份": "NY",
      "发货人城市": "JAMAICA",
      "发货邮编": "11413",
      "收货人姓名": "",
      "收货人电话": "",
      "收货人地址": "",
      "收货人省份": "",
      "收货人城市": "",
      "收件人邮编": "",
      "达到天数": "5",
      "商品ID": "",
      "重量(kg)": "0.31",
      "数量": "1",
      "货值(元)": "1000",
      "备注": "易碎物品，请小心搬运"
    }
  },
  "module2": {
    "mapping": {
      "sheinOrder": "GSP订单号",
      "sheinItem": "商品ID",
      "waybillOrder": "",
      "waybillTracking": "",
      "orderNumber": "",
      "itemId": ""
    },
    "fixed": {
      "logisticsProvider": "JCEX",
      "deleteFlag": "",
      "platformLogistics": "JCEX(US)",
      "shipType": "1"
    }
  },
  "savedAt": "2026-01-23T06:28:34.348Z"
}